bamboo_database/__init__.py
bamboo_database/py.typed
bamboo_database/adapters/__init__.py
bamboo_database/adapters/base.py
bamboo_database/adapters/factory.py
bamboo_database/adapters/mysql.py
bamboo_database/adapters/postgresql.py
bamboo_database/adapters/sqlite.py
bamboo_database/cli/__init__.py
bamboo_database/cli/main.py
bamboo_database/cli/commands/__init__.py
bamboo_database/cli/commands/generate_rules.py
bamboo_database/cli/commands/generate_schema.py
bamboo_database/cli/commands/list_databases.py
bamboo_database/cli/commands/mark.py
bamboo_database/cli/commands/migrate.py
bamboo_database/cli/commands/status.py
bamboo_database/config/__init__.py
bamboo_database/config/loader.py
bamboo_database/config/models.py
bamboo_database/migrations/__init__.py
bamboo_database/migrations/executor.py
bamboo_database/migrations/parser.py
bamboo_database/migrations/tracker.py
bamboo_database-0.1.2.dist-info/licenses/LICENSE
bamboo_database-0.1.2.dist-info/METADATA
bamboo_database-0.1.2.dist-info/WHEEL
bamboo_database-0.1.2.dist-info/entry_points.txt
bamboo_database-0.1.2.dist-info/top_level.txt
bamboo_database-0.1.2.dist-info/RECORD
