Metadata-Version: 2.4
Name: bamboo-database
Version: 0.1.2
Summary: CLI tool for managing database migrations and seed data across multiple backends
Author-email: Bamboo Tools <bamboo@bambooslips.xyz>
License: MIT
Project-URL: Homepage, https://github.com/tsl-bamboo/bamboo_database
Project-URL: Documentation, https://github.com/tsl-bamboo/bamboo_database#readme
Project-URL: Repository, https://github.com/tsl-bamboo/bamboo_database
Project-URL: Issues, https://github.com/tsl-bamboo/bamboo_database/issues
Keywords: database,migrations,seed,cli,postgresql,mysql,sqlite
Classifier: Development Status :: 3 - Alpha
Classifier: Environment :: Console
Classifier: Intended Audience :: Developers
Classifier: License :: OSI Approved :: MIT License
Classifier: Operating System :: OS Independent
Classifier: Programming Language :: Python :: 3
Classifier: Programming Language :: Python :: 3.10
Classifier: Programming Language :: Python :: 3.11
Classifier: Programming Language :: Python :: 3.12
Classifier: Topic :: Database
Classifier: Topic :: Software Development :: Libraries :: Python Modules
Classifier: Typing :: Typed
Requires-Python: >=3.10
License-File: LICENSE
Requires-Dist: tomli>=2.0.0; python_version < "3.11"
Provides-Extra: postgresql
Requires-Dist: psycopg[binary]>=3.0.0; extra == "postgresql"
Provides-Extra: mysql
Requires-Dist: mysql-connector-python>=8.0.0; extra == "mysql"
Provides-Extra: sqlite
Provides-Extra: all
Requires-Dist: psycopg[binary]>=3.0.0; extra == "all"
Requires-Dist: mysql-connector-python>=8.0.0; extra == "all"
Provides-Extra: dev
Requires-Dist: pytest>=7.0.0; extra == "dev"
Requires-Dist: pytest-cov>=4.0.0; extra == "dev"
Requires-Dist: ruff>=0.1.0; extra == "dev"
Requires-Dist: mypy>=1.0.0; extra == "dev"
Dynamic: license-file
